test_helper_gae3/__init__.py
test_helper_gae3-1.2.dist-info/LICENSE
test_helper_gae3-1.2.dist-info/METADATA
test_helper_gae3-1.2.dist-info/WHEEL
test_helper_gae3-1.2.dist-info/top_level.txt
test_helper_gae3-1.2.dist-info/RECORD
