Metadata-Version: 2.1
Name: test-helper-gae3
Version: 1.2
Summary: Class for autotests GoogleAppEngine python3 app.
Home-page: https://github.com/vb64/test.helper.gae3
Author: Vitaly Bogomolov
Author-email: mail@vitaly-bogomolov.ru
Project-URL: Bug Tracker, https://github.com/vb64/test.helper.gae3/issues
Classifier: Programming Language :: Python :: 3
Classifier: License :: OSI Approved :: MIT License
Classifier: Operating System :: OS Independent
Requires-Python: >=3.6
License-File: LICENSE
